{
"type": "FeatureCollection",
"name": "cheongna_rail_15",
"crs": { "type": "name", "properties": { "name": "urn:ogc:def:crs:OGC:1.3:CRS84" } },
"features": [
{ "type": "Feature", "properties": { "id": "287", "linenm": "인천2호선", "statnm": "검암", "x_5179": "927201.2207", "y_5179": "1952470.037", "lng": "126.67564317878316", "lat": "37.56872333769509", "begin": "2016-07-30", "effective_begin": null, "geometry_wkt": "POINT (927201.2207 1952470.037)", "origin_distance_m": 5494.8185916236816, "travel_time_min": 13.0 }, "geometry": { "type": "Point", "coordinates": [ 126.675643178783162, 37.56872333769509 ] } },
{ "type": "Feature", "properties": { "id": "288", "linenm": "인천2호선", "statnm": "검바위", "x_5179": "927360.3899", "y_5179": "1951638.675", "lng": "126.67752779099276", "lat": "37.5612431459511", "begin": "2016-07-30", "effective_begin": null, "geometry_wkt": "POINT (927360.3899 1951638.675)", "origin_distance_m": 5054.8710638090579, "travel_time_min": 14.75 }, "geometry": { "type": "Point", "coordinates": [ 126.677527790992755, 37.561243145951103 ] } },
{ "type": "Feature", "properties": { "id": "311", "linenm": "공항철도", "statnm": "운서", "x_5179": "911042.2679", "y_5179": "1944209.665", "lng": "126.49368716386016", "lat": "37.49285960419908", "begin": "2007-03-23", "effective_begin": null, "geometry_wkt": "POINT (911042.2679 1944209.665)", "origin_distance_m": 13077.960108313446, "travel_time_min": 12.0 }, "geometry": { "type": "Point", "coordinates": [ 126.493687163860159, 37.492859604199083 ] } },
{ "type": "Feature", "properties": { "id": "312", "linenm": "공항철도", "statnm": "영종", "x_5179": "913795.6603", "y_5179": "1946286.418", "lng": "126.52458657668389", "lat": "37.51183723123434", "begin": "2016-03-26", "effective_begin": null, "geometry_wkt": "POINT (913795.6603 1946286.418)", "origin_distance_m": 9849.317403224868, "travel_time_min": 8.0 }, "geometry": { "type": "Point", "coordinates": [ 126.524586576683888, 37.511837231234338 ] } },
{ "type": "Feature", "properties": { "id": "313", "linenm": "공항철도", "statnm": "청라국제도시", "x_5179": "922684.8519", "y_5179": "1951152.998", "lng": "126.62464505549165", "lat": "37.55648532952862", "begin": "2014-06-21", "effective_begin": null, "geometry_wkt": "POINT (922684.8519 1951152.998)", "origin_distance_m": 2726.4041848896268, "travel_time_min": 0.0 }, "geometry": { "type": "Point", "coordinates": [ 126.624645055491655, 37.556485329528627 ] } },
{ "type": "Feature", "properties": { "id": "314", "linenm": "공항철도", "statnm": "검암", "x_5179": "927028.4276", "y_5179": "1952529.439", "lng": "126.67368078052438", "lat": "37.56924502685766", "begin": "2007-03-23", "effective_begin": null, "geometry_wkt": "POINT (927028.4276 1952529.439)", "origin_distance_m": 5420.0077584203736, "travel_time_min": 5.0 }, "geometry": { "type": "Point", "coordinates": [ 126.673680780524379, 37.569245026857658 ] } },
{ "type": "Feature", "properties": { "id": "315", "linenm": "공항철도", "statnm": "계양", "x_5179": "932564.9583", "y_5179": "1952762.714", "lng": "126.73634885107874", "lat": "37.571769643436774", "begin": "2007-03-23", "effective_begin": null, "geometry_wkt": "POINT (932564.9583 1952762.714)", "origin_distance_m": 10116.68731796863, "travel_time_min": 12.0 }, "geometry": { "type": "Point", "coordinates": [ 126.736348851078745, 37.571769643436767 ] } }
]
}
